CodeVideoRenderer/CameraFollowCursorCVR.py
CodeVideoRenderer/__init__.py
CodeVideoRenderer/config.py
codevideorenderer-1.1.1.dist-info/METADATA
codevideorenderer-1.1.1.dist-info/WHEEL
codevideorenderer-1.1.1.dist-info/top_level.txt
codevideorenderer-1.1.1.dist-info/RECORD
