Metadata-Version: 2.1
Name: codevideorenderer
Version: 1.1.1
Summary: A Python library for rendering code videos
Author: Zhu Chongjing
Author-email: zhuchongjing_pypi@163.com
License: MIT
Classifier: Programming Language :: Python :: 3.9
Classifier: Programming Language :: Python :: 3.10
Classifier: Programming Language :: Python :: 3.11
Classifier: Programming Language :: Python :: 3.12
Classifier: Programming Language :: Python :: 3.13
Classifier: License :: OSI Approved :: MIT License
Classifier: Operating System :: OS Independent
Requires-Python: >=3.9
Requires-Dist: manim>=0.19.1
Requires-Dist: rich>=13.0.0
Requires-Dist: numpy
Requires-Dist: proglog
Requires-Dist: moviepy
Requires-Dist: pillow
